README.rst
setup.py
PDFutils.egg-info/PKG-INFO
PDFutils.egg-info/SOURCES.txt
PDFutils.egg-info/dependency_links.txt
PDFutils.egg-info/not-zip-safe
PDFutils.egg-info/requires.txt
PDFutils.egg-info/top_level.txt
pdfutils/__init__.py
pdfutils/models.py
pdfutils/reports.py
pdfutils/sites.py
pdfutils/utils.py