Metadata-Version: 1.1
Name: PDFutils
Version: 1.1.3
Summary: Django PDFutils
Home-page: https://github.com/h3/django-pdfutils
Author: Maxime Haineault
Author-email: haineault@gmail.com
License: BSD
Platform: UNKNOWN
Classifier: Development Status :: 3 - Alpha
Classifier: Environment :: Web Environment
Classifier: Intended Audience :: Developers
Classifier: License :: OSI Approved :: BSD License
Classifier: Operating System :: OS Independent
Classifier: Programming Language :: Python
Classifier: Framework :: Django
